{
  "timestamp": "2026-07-24T07:11:40.200Z",
  "thresholds": {
    "apiMs": 600,
    "pageMs": 4000
  },
  "summary": {
    "total": 11,
    "pass": 8,
    "slow": 3,
    "fail": 0,
    "skipped": 0,
    "netErrors": 0,
    "issues": 3
  },
  "api": [
    {
      "endpoint": "search",
      "query": "",
      "http_status": 200,
      "response_time_ms": 1024,
      "result": "SLOW",
      "detail": "1024ms > 600ms"
    },
    {
      "endpoint": "homepage",
      "query": "",
      "http_status": 200,
      "response_time_ms": 901,
      "result": "SLOW",
      "detail": "901ms > 600ms"
    },
    {
      "endpoint": "suggestions",
      "query": "toyota",
      "http_status": 200,
      "response_time_ms": 138,
      "result": "PASS",
      "detail": "cache?(Age:1890,X-Cache:Hit from cloudfront)"
    },
    {
      "endpoint": "suggestions",
      "query": "honda",
      "http_status": 200,
      "response_time_ms": 106,
      "result": "PASS",
      "detail": "cache?(Age:3592,X-Cache:Hit from cloudfront)"
    },
    {
      "endpoint": "suggestions",
      "query": "nissan",
      "http_status": 200,
      "response_time_ms": 106,
      "result": "PASS",
      "detail": "cache?(Age:3592,X-Cache:Hit from cloudfront)"
    },
    {
      "endpoint": "items",
      "query": "962133",
      "http_status": 200,
      "response_time_ms": 437,
      "result": "PASS",
      "detail": ""
    },
    {
      "endpoint": "items",
      "query": "986612",
      "http_status": 200,
      "response_time_ms": 379,
      "result": "PASS",
      "detail": ""
    },
    {
      "endpoint": "items",
      "query": "986568",
      "http_status": 200,
      "response_time_ms": 851,
      "result": "SLOW",
      "detail": "851ms > 600ms"
    }
  ],
  "journey": [
    {
      "step": "land",
      "url": "https://www.dubicars.com/",
      "load_time_ms": 1641,
      "result": "PASS",
      "detail": "7 non-critical request(s) ignored"
    },
    {
      "step": "search",
      "url": "https://www.dubicars.com/search?c=&ul=AE&ma=75&mo=1194&tr%5B%5D=&k=&cr=USD&eo%5B%5D=export-only&eo%5B%5D=can-be-exported",
      "load_time_ms": 2807,
      "result": "PASS",
      "detail": "search via typed input; 16 non-critical request(s) ignored"
    },
    {
      "step": "open_ad",
      "url": "https://www.dubicars.com/2025-nissan-navara-navara-25-diesel-pro4x-4x4-at-2025-my-engine-type-25d-mid-output-diesel-816770.html",
      "load_time_ms": 2350,
      "result": "PASS",
      "detail": "13 non-critical request(s) ignored"
    }
  ],
  "netErrors": []
}